[
  {"name": "air", "description": "Literally nothing, the void between blocks.", "value": 0, "rarity": 0},
  {"name": "stone", "description": "Solid rock foundation of Minecraft's underground world.", "value": 20, "rarity": 0},
  {"name": "granite", "description": "Speckled pink-red rock found deep underground.", "value": 15, "rarity": 1},
  {"name": "polished_granite", "description": "Smooth, refined version of rough granite.", "value": 25, "rarity": 1},
  {"name": "diorite", "description": "Light-colored speckled rock from deep caves.", "value": 15, "rarity": 1},
  {"name": "polished_diorite", "description": "Clean, smooth variant of natural diorite.", "value": 25, "rarity": 1},
  {"name": "andesite", "description": "Gray, medium-hardness rock common in mountainous regions.", "value": 15, "rarity": 1},
  {"name": "polished_andesite", "description": "Sleek, uniform surface of refined andesite.", "value": 25, "rarity": 1},
  {"name": "deepslate", "description": "Dark, dense stone found in deep underground layers.", "value": 30, "rarity": 2},
  {"name": "cobbled_deepslate", "description": "Rough, broken pieces of deepslate.", "value": 25, "rarity": 2},
  {"name": "polished_deepslate", "description": "Smooth, sophisticated version of raw deepslate.", "value": 35, "rarity": 2},
  {"name": "calcite", "description": "White, chalky mineral found in caves.", "value": 10, "rarity": 2},
  {"name": "tuff", "description": "Volcanic rock with a distinctive, rough texture.", "value": 15, "rarity": 2},
  {"name": "tuff_slab", "description": "Flat piece of tuff for smooth building.", "value": 20, "rarity": 2},
  {"name": "tuff_stairs", "description": "Volcanic rock stairs for architectural designs.", "value": 25, "rarity": 2},
  {"name": "tuff_wall", "description": "Defensive barrier made from volcanic rock.", "value": 30, "rarity": 2},
  {"name": "chiseled_tuff", "description": "Intricately carved tuff with decorative patterns.", "value": 40, "rarity": 3},
  {"name": "polished_tuff", "description": "Smooth, refined surface of volcanic tuff.", "value": 35, "rarity": 3},
  {"name": "polished_tuff_slab", "description": "Sleek, flat piece of processed tuff.", "value": 40, "rarity": 3},
  {"name": "polished_tuff_stairs", "description": "Elegant stairs crafted from smooth tuff.", "value": 45, "rarity": 3},
  {"name": "polished_tuff_wall", "description": "Sophisticated wall made from refined tuff.", "value": 50, "rarity": 3},
  {"name": "tuff_bricks", "description": "Structured bricks created from volcanic rock.", "value": 35, "rarity": 3},
  {"name": "tuff_brick_slab", "description": "Flat tuff brick for precise construction.", "value": 40, "rarity": 3},
  {"name": "tuff_brick_stairs", "description": "Decorative stairs made from tuff bricks.", "value": 45, "rarity": 3},
  {"name": "tuff_brick_wall", "description": "Fortified wall constructed from tuff bricks.", "value": 50, "rarity": 3},
  {"name": "chiseled_tuff_bricks", "description": "Elaborately carved tuff bricks with intricate design.", "value": 60, "rarity": 4},
  {"name": "dripstone_block", "description": "Pointy stone block found in cave systems.", "value": 25, "rarity": 2},
  {"name": "grass_block", "description": "Iconic green surface representing Minecraft's landscapes.", "value": 15, "rarity": 0},
  {"name": "dirt", "description": "Basic ground material, foundation of many worlds.", "value": 5, "rarity": 0},
  {"name": "coarse_dirt", "description": "Rough, less fertile version of standard dirt.", "value": 10, "rarity": 0},
  {"name": "podzol", "description": "Forest floor dirt with organic matter.", "value": 15, "rarity": 1},
  {"name": "rooted_dirt", "description": "Dirt block intertwined with plant roots.", "value": 20, "rarity": 1},
  {"name": "mud", "description": "Wet, squishy ground found in swamps.", "value": 10, "rarity": 1},
  {"name": "crimson_nylium", "description": "Vivid red-purple block from the Nether.", "value": 40, "rarity": 3},
  {"name": "warped_nylium", "description": "Striking blue-green block from Nether's warped forests.", "value": 40, "rarity": 3},
  {"name": "cobblestone", "description": "Rough stone blocks, classic Minecraft building material.", "value": 15, "rarity": 0},
  {"name": "oak_planks", "description": "Classic wooden planks from traditional oak trees.", "value": 25, "rarity": 0},
  {"name": "spruce_planks", "description": "Dark wooden planks from coniferous spruce trees.", "value": 25, "rarity": 0},
  {"name": "birch_planks", "description": "Light, pale wooden planks from birch trees.", "value": 25, "rarity": 0},
  {"name": "jungle_planks", "description": "Rich, warm-toned planks from dense jungle trees.", "value": 25, "rarity": 1},
  {"name": "acacia_planks", "description": "Reddish-brown planks from savanna's distinctive trees.", "value": 25, "rarity": 1},
  {"name": "cherry_planks", "description": "Delicate, light pink wooden planks from cherry trees.", "value": 35, "rarity": 2},
  {"name": "dark_oak_planks", "description": "Deep, almost black planks from massive dark oak.", "value": 25, "rarity": 1},
  {"name": "mangrove_planks", "description": "Unique reddish planks from swampy mangrove trees.", "value": 25, "rarity": 1},
  {"name": "bamboo_planks", "description": "Lightweight, sustainable planks crafted from bamboo.", "value": 30, "rarity": 2},
  {"name": "crimson_planks", "description": "Vibrant red planks from Nether's crimson forests.", "value": 35, "rarity": 3},
  {"name": "warped_planks", "description": "Mystical blue-green planks from Nether's warped forests.", "value": 35, "rarity": 3},
  {"name": "bamboo_mosaic", "description": "Decorative pattern created from interlocking bamboo planks.", "value": 35, "rarity": 3},
  {"name": "oak_sapling", "description": "Young tree ready to grow into a mighty oak.", "value": 15, "rarity": 0}
]